[
    {
        "date": "2021-03-23",
        "datetime": "2021-03-23T20:16:17.450Z",
        "package": "@ionic/react@5.6.3",
        "audits": {
            "scriptEvaluation": 354.43199999999996,
            "other": 73.96800000000009,
            "styleLayout": 43.172000000000004,
            "scriptParseCompile": 35.300000000000004,
            "parseHTML": 12.803999999999997,
            "paintCompositeRender": 7.455999999999988,
            "first-contentful-paint": 1716.8695000000002,
            "first-meaningful-paint": 1716.8695000000002,
            "load-fast-enough-for-pwa": 1716.8695000000002,
            "speed-index": 1716.8695000000002,
            "estimated-input-latency": 12.8,
            "total-blocking-time": 35.5,
            "max-potential-fid": 72,
            "time-to-first-byte": 9.389,
            "first-cpu-idle": 1716.8695000000002,
            "interactive": 1716.8695000000002,
            "mainthread-work-breakdown": 527.1320000000001,
            "bootup-time": 334.0760000000001,
            "network-requests": 18,
            "network-rtt": 0.063,
            "network-server-latency": 2.677,
            "main-thread-tasks": 4,
            "metrics": 1716.8695000000002,
            "total-byte-weight": 140667,
            "render-blocking-resources": 305,
            "dom-size": 81
        },
        "time": 1616530577450
    },
    {
        "date": "2021-03-24",
        "datetime": "2021-03-24T10:17:33.447Z",
        "package": "@ionic/react@5.6.3",
        "audits": {
            "scriptEvaluation": 379.34800000000035,
            "other": 82.86400000000005,
            "styleLayout": 51.412000000000006,
            "scriptParseCompile": 42.948,
            "parseHTML": 18.471999999999994,
            "paintCompositeRender": 9.659999999999986,
            "first-contentful-paint": 1727.3159999999998,
            "first-meaningful-paint": 1727.3159999999998,
            "load-fast-enough-for-pwa": 1727.3159999999998,
            "speed-index": 1727.3159999999998,
            "estimated-input-latency": 12.8,
            "total-blocking-time": 39.563999999999965,
            "max-potential-fid": 79,
            "time-to-first-byte": 9.821,
            "first-cpu-idle": 1727.3159999999998,
            "interactive": 1727.3159999999998,
            "mainthread-work-breakdown": 584.7040000000004,
            "bootup-time": 364.93600000000004,
            "network-requests": 18,
            "network-rtt": 0.045999999999999985,
            "network-server-latency": 2.3760000000000003,
            "main-thread-tasks": 4,
            "metrics": 1727.3159999999998,
            "total-byte-weight": 140667,
            "render-blocking-resources": 305,
            "dom-size": 81
        },
        "time": 1616581053447
    },
    {
        "date": "2021-03-24",
        "datetime": "2021-03-24T20:15:40.277Z",
        "package": "@ionic/react@5.6.3",
        "audits": {
            "scriptEvaluation": 321.28800000000007,
            "other": 67.84400000000001,
            "styleLayout": 41.996,
            "scriptParseCompile": 33.84799999999999,
            "parseHTML": 12.615999999999996,
            "paintCompositeRender": 7.767999999999989,
            "first-contentful-paint": 1702.708,
            "first-meaningful-paint": 1702.708,
            "load-fast-enough-for-pwa": 1702.708,
            "speed-index": 1702.708,
            "estimated-input-latency": 12.8,
            "total-blocking-time": 29,
            "max-potential-fid": 65,
            "time-to-first-byte": 18.616999999999997,
            "first-cpu-idle": 1702.708,
            "interactive": 1702.708,
            "mainthread-work-breakdown": 485.36,
            "bootup-time": 303.34800000000007,
            "network-requests": 18,
            "network-rtt": 0.04600000000000004,
            "network-server-latency": 2.4879999999999995,
            "main-thread-tasks": 4,
            "metrics": 1702.708,
            "total-byte-weight": 140667,
            "render-blocking-resources": 305,
            "dom-size": 81
        },
        "time": 1616616940277
    },
    {
        "date": "2021-03-25",
        "datetime": "2021-03-25T10:13:36.385Z",
        "package": "@ionic/react@5.6.3",
        "audits": {
            "scriptEvaluation": 258.23599999999993,
            "other": 71.08000000000004,
            "styleLayout": 42.727999999999994,
            "scriptParseCompile": 33.70399999999999,
            "parseHTML": 12.548,
            "paintCompositeRender": 8.055999999999989,
            "garbageCollection": 3.168,
            "first-contentful-paint": 1670.393,
            "first-meaningful-paint": 1670.393,
            "load-fast-enough-for-pwa": 1670.393,
            "speed-index": 1670.393,
            "estimated-input-latency": 12.8,
            "total-blocking-time": 13,
            "max-potential-fid": 49,
            "time-to-first-byte": 8.877,
            "first-cpu-idle": 1670.393,
            "interactive": 1670.393,
            "mainthread-work-breakdown": 429.52,
            "bootup-time": 240.45999999999998,
            "network-requests": 18,
            "network-rtt": 0.044999999999999984,
            "network-server-latency": 2.398,
            "main-thread-tasks": 4,
            "metrics": 1670.393,
            "total-byte-weight": 140667,
            "render-blocking-resources": 305,
            "dom-size": 81
        },
        "time": 1616667216385
    },
    {
        "date": "2021-03-25",
        "datetime": "2021-03-25T20:16:14.578Z",
        "package": "@ionic/react@5.6.3",
        "audits": {
            "scriptEvaluation": 299.61600000000067,
            "other": 82.22800000000001,
            "styleLayout": 44.916,
            "scriptParseCompile": 37.071999999999996,
            "parseHTML": 14.931999999999999,
            "paintCompositeRender": 9.015999999999988,
            "first-contentful-paint": 1687.6599999999999,
            "first-meaningful-paint": 1687.6599999999999,
            "load-fast-enough-for-pwa": 1687.6599999999999,
            "speed-index": 1687.6599999999999,
            "estimated-input-latency": 12.8,
            "total-blocking-time": 20.5,
            "max-potential-fid": 66.5,
            "time-to-first-byte": 10.012,
            "first-cpu-idle": 1687.6599999999999,
            "interactive": 1687.6599999999999,
            "mainthread-work-breakdown": 487.78000000000065,
            "bootup-time": 279.1040000000004,
            "network-requests": 18,
            "network-rtt": 0.043999999999999984,
            "network-server-latency": 2.7600000000000002,
            "main-thread-tasks": 4,
            "metrics": 1687.6599999999999,
            "total-byte-weight": 140667,
            "render-blocking-resources": 306,
            "dom-size": 81
        },
        "time": 1616703374578
    },
    {
        "date": "2021-03-26",
        "datetime": "2021-03-26T10:14:53.737Z",
        "package": "@ionic/react@5.6.3",
        "audits": {
            "scriptEvaluation": 290.88400000000064,
            "other": 85.15200000000004,
            "styleLayout": 48.540000000000006,
            "scriptParseCompile": 36.52800000000002,
            "parseHTML": 13.832000000000004,
            "paintCompositeRender": 8.763999999999989,
            "garbageCollection": 3.464,
            "first-contentful-paint": 1679.7685000000001,
            "first-meaningful-paint": 1679.7685000000001,
            "load-fast-enough-for-pwa": 1679.7685000000001,
            "speed-index": 1679.7685000000001,
            "estimated-input-latency": 12.8,
            "total-blocking-time": 16,
            "max-potential-fid": 61,
            "time-to-first-byte": 11.342,
            "first-cpu-idle": 1679.7685000000001,
            "interactive": 1679.7685000000001,
            "mainthread-work-breakdown": 487.1640000000007,
            "bootup-time": 264.22000000000025,
            "network-requests": 18,
            "network-rtt": 0.05699999999999994,
            "network-server-latency": 2.7910000000000004,
            "main-thread-tasks": 4,
            "metrics": 1679.7685000000001,
            "total-byte-weight": 140667,
            "render-blocking-resources": 306,
            "dom-size": 81
        },
        "time": 1616753693737
    },
    {
        "date": "2021-03-26",
        "datetime": "2021-03-26T20:18:58.645Z",
        "package": "@ionic/react@5.6.3",
        "audits": {
            "scriptEvaluation": 433.832000000001,
            "other": 93.12399999999997,
            "styleLayout": 47.708,
            "scriptParseCompile": 39.61200000000001,
            "parseHTML": 18.664,
            "paintCompositeRender": 8.53999999999999,
            "first-contentful-paint": 1740.042,
            "first-meaningful-paint": 1740.042,
            "load-fast-enough-for-pwa": 1740.042,
            "speed-index": 1740.042,
            "estimated-input-latency": 12.8,
            "total-blocking-time": 42.017999999999915,
            "max-potential-fid": 83.5,
            "time-to-first-byte": 38.714999999999996,
            "first-cpu-idle": 1740.042,
            "interactive": 1740.042,
            "mainthread-work-breakdown": 641.4800000000009,
            "bootup-time": 406.20800000000054,
            "network-requests": 18,
            "network-rtt": 0.04999999999999999,
            "network-server-latency": 3.0120000000000005,
            "main-thread-tasks": 5,
            "metrics": 1740.042,
            "total-byte-weight": 140667,
            "render-blocking-resources": 306,
            "dom-size": 81
        },
        "time": 1616789938645
    },
    {
        "date": "2021-03-27",
        "datetime": "2021-03-27T10:14:06.481Z",
        "package": "@ionic/react@5.6.3",
        "audits": {
            "scriptEvaluation": 318.864,
            "other": 83.98400000000005,
            "styleLayout": 42.344,
            "scriptParseCompile": 35.924,
            "parseHTML": 14.203999999999999,
            "paintCompositeRender": 9.391999999999992,
            "first-contentful-paint": 1696.8004999999998,
            "first-meaningful-paint": 1696.8004999999998,
            "load-fast-enough-for-pwa": 1696.8004999999998,
            "speed-index": 1696.8004999999998,
            "estimated-input-latency": 12.8,
            "total-blocking-time": 25,
            "max-potential-fid": 71,
            "time-to-first-byte": 10.734,
            "first-cpu-idle": 1696.8004999999998,
            "interactive": 1696.8004999999998,
            "mainthread-work-breakdown": 504.712,
            "bootup-time": 298.612,
            "network-requests": 18,
            "network-rtt": 0.07499999999999996,
            "network-server-latency": 2.9429999999999996,
            "main-thread-tasks": 5,
            "metrics": 1696.8004999999998,
            "total-byte-weight": 140667,
            "render-blocking-resources": 306,
            "dom-size": 81
        },
        "time": 1616840046481
    },
    {
        "date": "2021-03-27",
        "datetime": "2021-03-27T20:15:38.579Z",
        "package": "@ionic/react@5.6.3",
        "audits": {
            "scriptEvaluation": 267.50400000000053,
            "other": 64.92799999999998,
            "styleLayout": 41.92,
            "scriptParseCompile": 32.876000000000005,
            "parseHTML": 12.339999999999996,
            "paintCompositeRender": 7.259999999999993,
            "first-contentful-paint": 1679.4564999999998,
            "first-meaningful-paint": 1679.4564999999998,
            "load-fast-enough-for-pwa": 1679.4564999999998,
            "speed-index": 1679.4564999999998,
            "estimated-input-latency": 12.8,
            "total-blocking-time": 17,
            "max-potential-fid": 53.5,
            "time-to-first-byte": 8.803999999999998,
            "first-cpu-idle": 1679.4564999999998,
            "interactive": 1679.4564999999998,
            "mainthread-work-breakdown": 426.82800000000054,
            "bootup-time": 251.97600000000008,
            "network-requests": 18,
            "network-rtt": 0.07200000000000001,
            "network-server-latency": 2.559,
            "main-thread-tasks": 4,
            "metrics": 1679.4564999999998,
            "total-byte-weight": 140667,
            "render-blocking-resources": 305,
            "dom-size": 81
        },
        "time": 1616876138579
    },
    {
        "date": "2021-03-28",
        "datetime": "2021-03-28T10:14:13.888Z",
        "package": "@ionic/react@5.6.3",
        "audits": {
            "scriptEvaluation": 271.23600000000056,
            "other": 68.59200000000006,
            "styleLayout": 38.11599999999999,
            "scriptParseCompile": 34.923999999999985,
            "parseHTML": 13.628,
            "paintCompositeRender": 7.14399999999999,
            "first-contentful-paint": 1665.3229999999999,
            "first-meaningful-paint": 1665.3229999999999,
            "load-fast-enough-for-pwa": 1665.3229999999999,
            "speed-index": 1665.3229999999999,
            "estimated-input-latency": 12.8,
            "total-blocking-time": 16,
            "max-potential-fid": 49,
            "time-to-first-byte": 8.906,
            "first-cpu-idle": 1665.3229999999999,
            "interactive": 1665.3229999999999,
            "mainthread-work-breakdown": 433.64000000000055,
            "bootup-time": 252.41600000000028,
            "network-requests": 18,
            "network-rtt": 0.043999999999999984,
            "network-server-latency": 2.3779999999999997,
            "main-thread-tasks": 4,
            "metrics": 1665.3229999999999,
            "total-byte-weight": 140667,
            "render-blocking-resources": 305,
            "dom-size": 81
        },
        "time": 1616926453888
    },
    {
        "date": "2021-03-28",
        "datetime": "2021-03-28T20:15:36.183Z",
        "package": "@ionic/react@5.6.3",
        "audits": {
            "scriptEvaluation": 353.49600000000083,
            "other": 76.61199999999998,
            "scriptParseCompile": 44.492000000000026,
            "styleLayout": 38.688,
            "parseHTML": 21.712,
            "paintCompositeRender": 7.723999999999992,
            "first-contentful-paint": 1700.0725000000002,
            "first-meaningful-paint": 1700.0725000000002,
            "load-fast-enough-for-pwa": 1700.0725000000002,
            "speed-index": 1700.0725000000002,
            "estimated-input-latency": 12.8,
            "total-blocking-time": 31,
            "max-potential-fid": 64,
            "time-to-first-byte": 13.578000000000001,
            "first-cpu-idle": 1700.0725000000002,
            "interactive": 1700.0725000000002,
            "mainthread-work-breakdown": 542.7240000000008,
            "bootup-time": 332.6080000000001,
            "network-requests": 18,
            "network-rtt": 0.04400000000000004,
            "network-server-latency": 3.7350000000000003,
            "main-thread-tasks": 5,
            "metrics": 1700.0725000000002,
            "total-byte-weight": 140667,
            "render-blocking-resources": 307,
            "dom-size": 81
        },
        "time": 1616962536183
    },
    {
        "date": "2021-03-29",
        "datetime": "2021-03-29T10:15:08.410Z",
        "package": "@ionic/react@5.6.3",
        "audits": {
            "scriptEvaluation": 257.02400000000017,
            "other": 64.18399999999997,
            "styleLayout": 36.232,
            "scriptParseCompile": 34.768,
            "parseHTML": 16.255999999999997,
            "paintCompositeRender": 8.359999999999989,
            "first-contentful-paint": 1662.6685000000002,
            "first-meaningful-paint": 1662.6685000000002,
            "load-fast-enough-for-pwa": 1662.6685000000002,
            "speed-index": 1662.6685000000002,
            "estimated-input-latency": 12.8,
            "total-blocking-time": 15,
            "max-potential-fid": 48,
            "time-to-first-byte": 8.81,
            "first-cpu-idle": 1662.6685000000002,
            "interactive": 1662.6685000000002,
            "mainthread-work-breakdown": 416.82400000000007,
            "bootup-time": 242.62800000000001,
            "network-requests": 18,
            "network-rtt": 0.04799999999999999,
            "network-server-latency": 2.191,
            "main-thread-tasks": 4,
            "metrics": 1662.6685000000002,
            "total-byte-weight": 140667,
            "render-blocking-resources": 304,
            "dom-size": 81
        },
        "time": 1617012908410
    },
    {
        "date": "2021-03-29",
        "datetime": "2021-03-29T20:15:33.623Z",
        "package": "@ionic/react@5.6.3",
        "audits": {
            "scriptEvaluation": 263.78000000000054,
            "other": 67.22000000000001,
            "styleLayout": 37.547999999999995,
            "scriptParseCompile": 34.583999999999996,
            "parseHTML": 13.136000000000001,
            "paintCompositeRender": 7.251999999999989,
            "first-contentful-paint": 1662.5365,
            "first-meaningful-paint": 1662.5365,
            "load-fast-enough-for-pwa": 1662.5365,
            "speed-index": 1662.5365,
            "estimated-input-latency": 12.8,
            "total-blocking-time": 14.5,
            "max-potential-fid": 47.5,
            "time-to-first-byte": 8.749,
            "first-cpu-idle": 1662.5365,
            "interactive": 1662.5365,
            "mainthread-work-breakdown": 423.5200000000006,
            "bootup-time": 246.10000000000008,
            "network-requests": 18,
            "network-rtt": 0.04500000000000004,
            "network-server-latency": 2.439,
            "main-thread-tasks": 4,
            "metrics": 1662.5365,
            "total-byte-weight": 140667,
            "render-blocking-resources": 305,
            "dom-size": 81
        },
        "time": 1617048933623
    },
    {
        "date": "2021-03-30",
        "datetime": "2021-03-30T10:17:14.579Z",
        "package": "@ionic/react@5.6.3",
        "audits": {
            "scriptEvaluation": 410.4280000000012,
            "other": 177.73600000000005,
            "styleLayout": 76.35200000000002,
            "scriptParseCompile": 39.99200000000001,
            "paintCompositeRender": 27.86400000000001,
            "parseHTML": 18.035999999999998,
            "first-contentful-paint": 1742.1220000000003,
            "first-meaningful-paint": 1742.1220000000003,
            "load-fast-enough-for-pwa": 1775.1220000000003,
            "speed-index": 1742.1220000000003,
            "estimated-input-latency": 12.8,
            "total-blocking-time": 46,
            "max-potential-fid": 96,
            "time-to-first-byte": 16.643,
            "first-cpu-idle": 1742.1220000000003,
            "interactive": 1775.1220000000003,
            "mainthread-work-breakdown": 750.4080000000012,
            "bootup-time": 380.9360000000004,
            "network-requests": 18,
            "network-rtt": 0.08400000000000007,
            "network-server-latency": 5.8919999999999995,
            "main-thread-tasks": 7,
            "metrics": 1775.1220000000003,
            "total-byte-weight": 140667,
            "render-blocking-resources": 312,
            "dom-size": 81
        },
        "time": 1617099434579
    },
    {
        "date": "2021-03-30",
        "datetime": "2021-03-30T20:18:23.732Z",
        "package": "@ionic/react@5.6.3",
        "audits": {
            "scriptEvaluation": 360.36400000000054,
            "other": 111.41199999999998,
            "styleLayout": 73.34,
            "scriptParseCompile": 40.855999999999995,
            "parseHTML": 36.54800000000001,
            "paintCompositeRender": 10.311999999999987,
            "first-contentful-paint": 1706.8349999999998,
            "first-meaningful-paint": 1706.8349999999998,
            "load-fast-enough-for-pwa": 1732.8349999999998,
            "speed-index": 1706.8349999999998,
            "estimated-input-latency": 12.8,
            "total-blocking-time": 25.5,
            "max-potential-fid": 75.5,
            "time-to-first-byte": 12.084999999999999,
            "first-cpu-idle": 1706.8349999999998,
            "interactive": 1732.8349999999998,
            "mainthread-work-breakdown": 632.8320000000006,
            "bootup-time": 329.03200000000027,
            "network-requests": 18,
            "network-rtt": 0.12300000000000005,
            "network-server-latency": 3.8099999999999996,
            "main-thread-tasks": 6,
            "metrics": 1732.8349999999998,
            "total-byte-weight": 140667,
            "render-blocking-resources": 308,
            "dom-size": 81
        },
        "time": 1617135503732
    }
]