[
    {
        "date": "2020-12-10",
        "datetime": "2020-12-10T10:13:52.575Z",
        "package": "@ionic/react@5.5.2",
        "audits": {
            "scriptEvaluation": 417.50800000000226,
            "other": 91.3880000000002,
            "styleLayout": 52.92,
            "scriptParseCompile": 39.87199999999999,
            "parseHTML": 18.771999999999995,
            "paintCompositeRender": 8.855999999999991,
            "first-contentful-paint": 1709.0935,
            "first-meaningful-paint": 1709.0935,
            "load-fast-enough-for-pwa": 1709.0935,
            "speed-index": 1709.0935,
            "estimated-input-latency": 12.8,
            "total-blocking-time": 29.5,
            "max-potential-fid": 76,
            "time-to-first-byte": 10.234000000000002,
            "first-cpu-idle": 1709.0935,
            "interactive": 1709.0935,
            "mainthread-work-breakdown": 629.3160000000024,
            "bootup-time": 380.4320000000009,
            "network-requests": 25,
            "network-rtt": 0.045999999999999985,
            "network-server-latency": 2.741,
            "main-thread-tasks": 6,
            "metrics": 1709.0935,
            "total-byte-weight": 144410,
            "render-blocking-resources": 305,
            "dom-size": 276
        },
        "time": 1607595232575
    }
]